[
  {
    "featureType": "administrative",
    "elementType": "labels.text.fill",
    "stylers": [
      {
        "color": "#676f8f"
      }
    ]
  },
  {
    "featureType": "administrative.country",
    "elementType": "geometry.stroke",
    "stylers": [
      {
        "color": "#ced0f3"
      }
    ]
  },
  {
    "featureType": "administrative.land_parcel",
    "stylers": [
      {
        "visibility": "off"
      }
    ]
  },
  {
    "featureType": "administrative.neighborhood",
    "stylers": [
      {
        "visibility": "off"
      }
    ]
  },
  {
    "featureType": "administrative.neighborhood",
    "elementType": "labels",
    "stylers": [
      {
        "visibility": "off"
      }
    ]
  },
  {
    "featureType": "landscape.man_made",
    "elementType": "geometry.fill",
    "stylers": [
      {
        "color": "#f2f3f9"
      }
    ]
  },
  {
    "featureType": "landscape.man_made",
    "elementType": "geometry.stroke",
    "stylers": [
      {
        "color": "#f2f3f9"
      },
      {
        "weight": 0.5
      }
    ]
  },
  {
    "featureType": "landscape.natural",
    "elementType": "geometry.fill",
    "stylers": [
      {
        "color": "#f2f3f9"
      }
    ]
  },
  {
    "featureType": "landscape.natural",
    "elementType": "geometry.stroke",
    "stylers": [
      {
        "visibility": "off"
      }
    ]
  },
  {
    "featureType": "landscape.natural",
    "elementType": "labels.icon",
    "stylers": [
      {
        "visibility": "off"
      }
    ]
  },
  {
    "featureType": "landscape.natural.landcover",
    "elementType": "geometry.fill",
    "stylers": [
      {
        "color": "#f2f3f9"
      }
    ]
  },
  {
    "featureType": "landscape.natural.landcover",
    "elementType": "geometry.stroke",
    "stylers": [
      {
        "color": "#f2f3f9"
      }
    ]
  },
  {
    "featureType": "landscape.natural.terrain",
    "elementType": "geometry.fill",
    "stylers": [
      {
        "color": "#f2f3f9"
      },
      {
        "weight": 0.5
      }
    ]
  },
  {
    "featureType": "poi",
    "elementType": "geometry.fill",
    "stylers": [
      {
        "color": "#ebedff"
      }
    ]
  },
  {
    "featureType": "poi",
    "elementType": "labels.icon",
    "stylers": [
      {
        "color": "#a8b2ff"
      }
    ]
  },
  {
    "featureType": "poi",
    "elementType": "labels.text",
    "stylers": [
      {
        "visibility": "off"
      }
    ]
  },
  {
    "featureType": "poi.attraction",
    "elementType": "geometry.fill",
    "stylers": [
      {
        "color": "#b9f2ab"
      }
    ]
  },
  {
    "featureType": "poi.business",
    "stylers": [
      {
        "visibility": "off"
      }
    ]
  },
  {
    "featureType": "poi.business",
    "elementType": "labels",
    "stylers": [
      {
        "visibility": "on"
      }
    ]
  },
  {
    "featureType": "poi.business",
    "elementType": "labels.text",
    "stylers": [
      {
        "visibility": "off"
      }
    ]
  },
  {
    "featureType": "poi.business",
    "elementType": "labels.text.fill",
    "stylers": [
      {
        "color": "#7783e4"
      }
    ]
  },
  {
    "featureType": "poi.park",
    "elementType": "geometry.fill",
    "stylers": [
      {
        "color": "#bdf0bc"
      }
    ]
  },
  {
    "featureType": "poi.sports_complex",
    "elementType": "geometry.fill",
    "stylers": [
      {
        "color": "#d5d7fb"
      }
    ]
  },
  {
    "featureType": "road",
    "elementType": "geometry.stroke",
    "stylers": [
      {
        "visibility": "off"
      }
    ]
  },
  {
    "featureType": "road",
    "elementType": "labels.icon",
    "stylers": [
      {
        "visibility": "off"
      }
    ]
  },
  {
    "featureType": "road",
    "elementType": "labels.text.fill",
    "stylers": [
      {
        "color": "#676f8f"
      }
    ]
  },
  {
    "featureType": "road.highway",
    "elementType": "geometry.fill",
    "stylers": [
      {
        "color": "#dbe0f9"
      }
    ]
  },
  {
    "featureType": "transit",
    "stylers": [
      {
        "visibility": "off"
      }
    ]
  },
  {
    "featureType": "transit.station.airport",
    "elementType": "geometry.fill",
    "stylers": [
      {
        "color": "#dbe0f9"
      }
    ]
  },
  {
    "featureType": "water",
    "elementType": "geometry.fill",
    "stylers": [
      {
        "color": "#b8e3fc"
      }
    ]
  },
  {
    "featureType": "water",
    "elementType": "labels.text.fill",
    "stylers": [
      {
        "color": "#8db5f7"
      }
    ]
  }
]